rcdata/__init__.py
rcdata/base.py
rcdata/io.py
rcdata/res.py
rcdata-0.4.1.dist-info/WHEEL
rcdata-0.4.1.dist-info/METADATA
rcdata-0.4.1.dist-info/licenses/LICENSE
rcdata-0.4.1.dist-info/RECORD
